palabros/__init__.py
palabros/business.py
palabros/console.py
palabros/database.py
palabros/errors.py
palabros/main.py
palabros/queries.py
palabros/schemas.py
palabros/words.json
palabros-0.0.6.dist-info/entry_points.txt
palabros-0.0.6.dist-info/LICENSE
palabros-0.0.6.dist-info/WHEEL
palabros-0.0.6.dist-info/METADATA
palabros-0.0.6.dist-info/RECORD
