Metadata-Version: 2.1
Name: palabros
Version: 0.0.6
Summary: Este CLI no es más que clon de Wordle en español
Home-page: https://github.com/vermicida/palabros
License: MIT
Keywords: juego,game,juegos,games,palabra,word,palabras,words,wordle
Author: Diego Herrera
Author-email: vermicida@gmail.com
Requires-Python: >=3.8,<4.0
Classifier: Development Status :: 3 - Alpha
Classifier: Intended Audience :: Developers
Classifier: License :: OSI Approved :: MIT License
Classifier: Operating System :: OS Independent
Classifier: Programming Language :: Python :: 3
Classifier: Programming Language :: Python :: 3.10
Classifier: Programming Language :: Python :: 3.8
Classifier: Programming Language :: Python :: 3.9
Classifier: Topic :: Software Development :: Libraries :: Python Modules
Requires-Dist: rich (>=11.1.0,<12.0.0)
Requires-Dist: typer (>=0.4.0,<0.5.0)
Project-URL: Repository, https://github.com/vermicida/palabros
